usvfs/__init__.py
usvfs/_usvfs_dll.pyd
usvfs/usvfs_proxy_x64.exe
usvfs/usvfs_proxy_x86.exe
usvfs/usvfs_wrapper.py
usvfs/usvfs_x86.dll
py_usvfs-0.2.0.dist-info/LICENSE
py_usvfs-0.2.0.dist-info/METADATA
py_usvfs-0.2.0.dist-info/WHEEL
py_usvfs-0.2.0.dist-info/top_level.txt
py_usvfs-0.2.0.dist-info/RECORD
