Metadata-Version: 2.1
Name: py-usvfs
Version: 0.2.0
Summary: Python bindings for the userspace virtual filesystem (usvfs) library
Home-page: https://github.com/pwssnk/py-usvfs
Author: pwssnk
Author-email: 
License: UNKNOWN
Platform: UNKNOWN
Classifier: Development Status :: 3 - Alpha
Classifier: License :: OSI Approved :: GNU Lesser General Public License v3 (LGPLv3)
Classifier: Operating System :: Microsoft :: Windows
Classifier: Programming Language :: Python :: 3.7
Classifier: Programming Language :: Python :: Implementation :: CPython
Classifier: Topic :: System :: Filesystems
Requires-Python: >=3.7
